setup.cfg
setup.py
cgquery_xml_to_bamlibrary_capture_json/__init__.py
cgquery_xml_to_bamlibrary_capture_json/__main__.py
cgquery_xml_to_bamlibrary_capture_json/main.py
cgquery_xml_to_bamlibrary_capture_json.egg-info/PKG-INFO
cgquery_xml_to_bamlibrary_capture_json.egg-info/SOURCES.txt
cgquery_xml_to_bamlibrary_capture_json.egg-info/dependency_links.txt
cgquery_xml_to_bamlibrary_capture_json.egg-info/entry_points.txt
cgquery_xml_to_bamlibrary_capture_json.egg-info/top_level.txt