Metadata-Version: 1.1
Name: cgquery-xml-to-bamlibrary-capture-json
Version: 0.2
Summary: convert cgquery sra xml to capture_kits/target_set json
Home-page: https://github.com/jeremiahsavage/cgquery_xml_to_bamlibrary_capture_json/
Author: Jeremiah H. Savage
Author-email: jeremiahsavage@gmail.com
License: Apache 2.0
Platform: UNKNOWN
Classifier: Development Status :: 3 - Alpha
Classifier: Intended Audience :: Developers
Classifier: License :: OSI Approved :: Apache Software License
Classifier: Programming Language :: Python
Classifier: Programming Language :: Python :: 2
Classifier: Programming Language :: Python :: 3
